<?xml version="1.0" encoding="UTF-8" ?>
<!DOCTYPE configuration PUBLIC "-//mybatis.org//DTD Config 3.0//EN"
        "http://mybatis.org/dtd/mybatis-3-config.dtd">

<configuration>
    <typeAliases>
        <typeAlias alias="User" type="ims.manager.domain.User"/>
        <typeAlias alias="UserLoginLog" type="ims.manager.domain.UserLoginLog"/>
        
        <typeAlias alias="Factory" type="ims.factory.domain.Factory"/>
        <typeAlias alias="Order" type="ims.order.domain.Order"/>
        <typeAlias alias="OrderDetails" type="ims.order.domain.OrderDetails"/>
        <typeAlias alias="Product" type="ims.product.domain.Product"/>
        <typeAlias alias="Props" type="ims.props.domain.Props"/>
        <typeAlias alias="PropsDetails" type="ims.props.domain.PropsDetails"/>
        
    </typeAliases>
</configuration>